classifyspectraltype/__init__.py
classifyspectraltype/boxplot_table_function.py
classifyspectraltype/clean_confidence_intervals.py
classifyspectraltype/fetch_exoplanet_dataset.py
classifyspectraltype/split_cross_val.py
classifyspectraltype-0.3.0.dist-info/LICENSE
classifyspectraltype-0.3.0.dist-info/METADATA
classifyspectraltype-0.3.0.dist-info/WHEEL
classifyspectraltype-0.3.0.dist-info/RECORD
